dataloom_common/__init__.py
dataloom_common/logging.py
dataloom_common/tenants.py
dataloom_common/data_sources/__init__.py
dataloom_common/data_sources/base.py
dataloom_common/data_sources/excel.py
dataloom_common/data_sources/postgres.py
dataloom_common/data_sources/quickbooks.py
dataloom_common/data_sources/snowflake.py
dataloom_common/data_sources/warehouse.py
dataloom_common/sample_data/excel_demo.csv
dataloom_common/sample_data/finance_demo.csv
dataloom_common/sample_data/overview_demo.csv
dataloom_common/sample_data/pipeline_demo.csv
dataloom_common/sample_data/quickbooks_demo.json
dataloom_common/sample_data/sales_demo.csv
dataloom_common/sample_data/tenants.json
dataloom_common-0.2.2.dist-info/METADATA
dataloom_common-0.2.2.dist-info/WHEEL
dataloom_common-0.2.2.dist-info/top_level.txt
dataloom_common-0.2.2.dist-info/RECORD
