Metadata-Version: 2.4
Name: dataloom-common
Version: 0.2.2
Summary: Shared utilities and data adapters for DataLoom tier starters.
Requires-Python: >=3.10
Requires-Dist: pandas>=2.3
Requires-Dist: numpy>=2.3
Requires-Dist: sqlalchemy>=2.0
